owc/__init__.py
owc/__main__.py
owc/owc.py
one_word_captions-1.0.0.dist-info/METADATA
one_word_captions-1.0.0.dist-info/WHEEL
one_word_captions-1.0.0.dist-info/entry_points.txt
one_word_captions-1.0.0.dist-info/top_level.txt
one_word_captions-1.0.0.dist-info/RECORD
