Metadata-Version: 2.2
Name: one-word-captions
Version: 1.0.0
Summary: Generate synchronized one-word captions for videos using WhisperX timestamps
Author: Xabi Ezpeleta
Project-URL: Homepage, https://github.com/xezpeleta/one-word-captions
Project-URL: Bug Tracker, https://github.com/xezpeleta/one-word-captions/issues
Keywords: captions,video,whisperx,subtitles
Classifier: Development Status :: 3 - Alpha
Classifier: Programming Language :: Python :: 3
Classifier: Programming Language :: Python :: 3.8
Classifier: Programming Language :: Python :: 3.9
Classifier: Programming Language :: Python :: 3.10
Requires-Python: >=3.8
Provides-Extra: dev
Requires-Dist: pytest>=7.0.0; extra == "dev"
Requires-Dist: pytest-cov>=4.0.0; extra == "dev"
Requires-Dist: black>=23.0.0; extra == "dev"
Requires-Dist: isort>=5.12.0; extra == "dev"
Requires-Dist: flake8>=6.0.0; extra == "dev"
Requires-Dist: mypy>=1.0.0; extra == "dev"
Requires-Dist: setuptools; extra == "dev"
Requires-Dist: wheel; extra == "dev"
